{
  "variants": {
    "facing=south,half=lower": {
      "model": "the_vault:block/vending_machine"
    },
    "facing=east,half=lower": {
      "model": "the_vault:block/vending_machine",
      "y": 270
    },
    "facing=north,half=lower": {
      "model": "the_vault:block/vending_machine",
      "y": 180
    },
    "facing=west,half=lower": {
      "model": "the_vault:block/vending_machine",
      "y": 90
    },
    "facing=south,half=upper": {
      "model": "the_vault:block/vending_machine_top"
    },
    "facing=east,half=upper": {
      "model": "the_vault:block/vending_machine_top",
      "y": 270
    },
    "facing=north,half=upper": {
      "model": "the_vault:block/vending_machine_top",
      "y": 180
    },
    "facing=west,half=upper": {
      "model": "the_vault:block/vending_machine_top",
      "y": 90
    }
  }
}